evilvars/LICENSE
evilvars/README.md
evilvars/__init__.py
evilvars/requirements.txt
evilvars/thirdparty.json
evilvars-0.10.dist-info/LICENSE.rst
evilvars-0.10.dist-info/METADATA
evilvars-0.10.dist-info/WHEEL
evilvars-0.10.dist-info/top_level.txt
evilvars-0.10.dist-info/RECORD
