Metadata-Version: 2.1
Name: evilvars
Version: 0.10
Summary: Changes immutable data types (in-place)
Home-page: https://github.com/hansalemaos/evilvars
Author: Johannes Fischer
Author-email: aulasparticularesdealemaosp@gmail.com
License: MIT
Keywords: ctypes,low-level,evil,Change immutable data types
Classifier: Development Status :: 4 - Beta
Classifier: Programming Language :: Python :: 3 :: Only
Classifier: Programming Language :: Python :: 3.10
Classifier: Topic :: Software Development :: Libraries :: Python Modules
Classifier: Topic :: Utilities
License-File: LICENSE.rst
Requires-Dist: numpy
